Workbook
Name aporte: Simulador!$D$12
Name patrimonio: Simulador!$D$15
Name qtd_anos: Simulador!$D$13
Name rendimento_carteira: Simulador!$D$8
Name salario: Simulador!$D$7
Name sugestao_investimento: Simulador!$D$9
Name taxa_mensal: Simulador!$D$14

Sheet Simulador
B6: Configurações
B7: Salário | D7: 2000
B8: Rendimento de Carteira | D8: 0.0089
B9: Sugestão de Investimentos | D9: =D7*30% -> 600
B11: INVESTIMENTO MENSAL
B12: Quanto investir por mês | D12: 200
B13: Por Quantos Anos? | D13: 5
B14: Taxa de Rendimento Mensal? | D14: 0.01079
B15: Patrimônio Acumulado? | D15: =FV(taxa_mensal,qtd_anos*12,aporte*-1) -> 16755.383
B16: Dividendos Mensais? | D16: =patrimonio*rendimento_carteira -> 149.12291
B18: Cenários | D18: Dividendos
A19: 2 | B19: Quanto em 02 anos? | C19: =FV($D$14,$A19*12,$D$12*-1) -> 5445.5255 | D19: =C19*rendimento_carteira -> 48.465177
A20: 5 | B20: Quanto em 05 anos? | C20: =FV($D$14,$A20*12,$D$12*-1) -> 16755.383 | D20: =C20*rendimento_carteira -> 149.12291
A21: 10 | B21: Quanto em 10 anos? | C21: =FV($D$14,$A21*12,$D$12*-1) -> 48656.843 | D21: =C21*rendimento_carteira -> 433.0459
A22: 20 | B22: Quanto em 20 anos? | C22: =FV($D$14,$A22*12,$D$12*-1) -> 225039.68 | D22: =C22*rendimento_carteira -> 2002.8532
A23: 30 | B23: Quanto em 30 anos? | C23: =FV($D$14,$A23*12,$D$12*-1) -> 864433.93 | D23: =C23*rendimento_carteira -> 7693.462
B25: Perfil | C25: Agressivo
B26: VALOR A SER INVESTIDO POR MÊS | C26: =aporte -> 200
B28: TIPO DE FII | C28: Percentual Sugerido | D28: Valores
B29: PAPEL | C29: =VLOOKUP($C$25&"-"&B29,PlanRef!$B$2:$E$20,4,FALSE) -> 0.5 | D29: =C29*$C$26 -> 100
B30: TIJOLO | C30: =VLOOKUP($C$25&"-"&B30,PlanRef!$B$2:$E$20,4,FALSE) -> 0.1 | D30: =C30*$C$26 -> 20
B31: HIBRIDOS | C31: =VLOOKUP($C$25&"-"&B31,PlanRef!$B$2:$E$20,4,FALSE) -> 0.05 | D31: =C31*$C$26 -> 10
B32: FOFs | C32: =VLOOKUP($C$25&"-"&B32,PlanRef!$B$2:$E$20,4,FALSE) -> 0.05 | D32: =C32*$C$26 -> 10
B33: DESENVOLVIMENTO | C33: =VLOOKUP($C$25&"-"&B33,PlanRef!$B$2:$E$20,4,FALSE) -> 0.2 | D33: =C33*$C$26 -> 40
B34: HOTELARIA | C34: =VLOOKUP($C$25&"-"&B34,PlanRef!$B$2:$E$20,4,FALSE) -> 0.1 | D34: =C34*$C$26 -> 20
D35: =SUM(D29:D34) -> 200

Sheet PlanRef
B2: Chave | C2: Perfil | D2: TIPO DE FII | E2: Percent
B3: =$C$3&"-"&D3 -> Agressivo-PAPEL | C3: Agressivo | D3: PAPEL | E3: 0.5
B4: =$C$3&"-"&D4 -> Agressivo-TIJOLO | C4: Agressivo | D4: TIJOLO | E4: 0.1
B5: =$C$3&"-"&D5 -> Agressivo-HIBRIDOS | C5: Agressivo | D5: HIBRIDOS | E5: 0.05
B6: =$C$3&"-"&D6 -> Agressivo-FOFs | C6: Agressivo | D6: FOFs | E6: 0.05
B7: =$C$3&"-"&D7 -> Agressivo-DESENVOLVIMENTO | C7: Agressivo | D7: DESENVOLVIMENTO | E7: 0.2
B8: =$C$3&"-"&D8 -> Agressivo-HOTELARIA | C8: Agressivo | D8: HOTELARIA | E8: 0.1
B9: =$C$9&"-"&D9 -> Moderado-PAPEL | C9: Moderado | D9: PAPEL | E9: 0.22
B10: =$C$9&"-"&D10 -> Moderado-TIJOLO | C10: Moderado | D10: TIJOLO | E10: 0.4
B11: =$C$9&"-"&D11 -> Moderado-HIBRIDOS | C11: Moderado | D11: HIBRIDOS | E11: 0.08
B12: =$C$9&"-"&D12 -> Moderado-FOFs | C12: Moderado | D12: FOFs | E12: 0.1
B13: =$C$9&"-"&D13 -> Moderado-DESENVOLVIMENTO | C13: Moderado | D13: DESENVOLVIMENTO | E13: 0.1
B14: =$C$9&"-"&D14 -> Moderado-HOTELARIA | C14: Moderado | D14: HOTELARIA | E14: 0.1
B15: =$C$15&"-"&D15 -> Conservador-PAPEL | C15: Conservador | D15: PAPEL | E15: 0.3
B16: =$C$15&"-"&D16 -> Conservador-TIJOLO | C16: Conservador | D16: TIJOLO | E16: 0.5
B17: =$C$15&"-"&D17 -> Conservador-HIBRIDOS | C17: Conservador | D17: HIBRIDOS | E17: 0.1
B18: =$C$15&"-"&D18 -> Conservador-FOFs | C18: Conservador | D18: FOFs | E18: 0.0971
B19: =$C$15&"-"&D19 -> Conservador-DESENVOLVIMENTO | C19: Conservador | D19: DESENVOLVIMENTO | E19: 0.001
B20: =$C$15&"-"&D20 -> Conservador-HOTELARIA | C20: Conservador | D20: HOTELARIA | E20: 0.0019
A39: Quanto investir por mês
A40: Por Quantos Anos?
A41: Taxa de Rendimento Mensal?
A42: Patrimônio Acumulado?
A43: Dividendos Mensais?
A45: CTRL + F3 | B45: Abre lista de nomes de células
